fsync/__init__.py
fsync/cli.py
fsync/core.py
fsync/report.py
fsync_conscious-0.2.0.dist-info/LICENSE
fsync_conscious-0.2.0.dist-info/METADATA
fsync_conscious-0.2.0.dist-info/WHEEL
fsync_conscious-0.2.0.dist-info/entry_points.txt
fsync_conscious-0.2.0.dist-info/top_level.txt
fsync_conscious-0.2.0.dist-info/RECORD
