Metadata-Version: 2.2
Name: fsync-conscious
Version: 0.2.0
Summary: Conscious filesystem diff, audit and sync tool
Author: Rafael Sanches
License: MIT
Requires-Python: >=3.9
License-File: LICENSE
Provides-Extra: dev
Requires-Dist: pytest>=7.0; extra == "dev"
Requires-Dist: jsonschema>=4.0; extra == "dev"
